bossbot/__init__.py
bossbot/bossbot.py
bossbot/proto_pb2.py
bossbot/protobuf_json.py
examples/__init__.py
examples/bossBot_test.py
bossbot-0.3.dist-info/METADATA
bossbot-0.3.dist-info/WHEEL
bossbot-0.3.dist-info/top_level.txt
bossbot-0.3.dist-info/RECORD
