Metadata-Version: 2.1
Name: bossbot
Version: 0.3
Summary: A boss chat bot
Home-page: https://github.com/wangyitao/cbot
Author: xmq
Author-email: jiongbo416jie@qq.com
Maintainer: xmq
Maintainer-email: jiongbo416jie@qq.com
License: MIT License
Platform: all
Classifier: Development Status :: 4 - Beta
Classifier: Operating System :: OS Independent
Classifier: Intended Audience :: Developers
Classifier: License :: OSI Approved :: MIT License
Classifier: Programming Language :: Python
Classifier: Programming Language :: Python :: Implementation
Classifier: Programming Language :: Python :: 3.4
Classifier: Programming Language :: Python :: 3.5
Classifier: Programming Language :: Python :: 3.6
Classifier: Topic :: Software Development :: Libraries
Requires-Dist: paho-mqtt
Requires-Dist: protobuf
Requires-Dist: qrcode
Requires-Dist: requests
Requires-Dist: Pillow
